aggiestack/__init__.py
aggiestack/__main__.py
aggiestack/cli.py
aggiestack/commands/__init__.py
aggiestack/commands/admin.py
aggiestack/commands/base.py
aggiestack/commands/config.py
aggiestack/commands/server.py
aggiestack/commands/show.py
aggiestack/commands/utils.py
aggiestack/utils/__init__.py
aggiestack/utils/connect_db.py
aggiestack/utils/database.py
aggiestack/utils/flavor_utils.py
aggiestack/utils/hardware_utils.py
aggiestack/utils/image_utils.py
aggiestack/utils/instance_utils.py
aggiestack/utils/logger.py
aggiestack-1.0.5.dist-info/DESCRIPTION.rst
aggiestack-1.0.5.dist-info/METADATA
aggiestack-1.0.5.dist-info/RECORD
aggiestack-1.0.5.dist-info/WHEEL
aggiestack-1.0.5.dist-info/entry_points.txt
aggiestack-1.0.5.dist-info/metadata.json
aggiestack-1.0.5.dist-info/top_level.txt
